leicaimage/__init__.py
leicaimage/experiment.py
leicaimage/py.typed
leicaimage-0.4.0.dist-info/LICENSE
leicaimage-0.4.0.dist-info/METADATA
leicaimage-0.4.0.dist-info/WHEEL
leicaimage-0.4.0.dist-info/RECORD
