Metadata-Version: 2.1
Name: leicaimage
Version: 0.4.0
Summary: Handle Leica Matrix Screener experiment images.
Home-page: https://github.com/MartinHjelmare/leicaimage
License: MIT
Author: Martin Hjelmare
Author-email: marhje52@gmail.com
Requires-Python: >=3.9,<4.0
Classifier: Development Status :: 3 - Alpha
Classifier: Intended Audience :: Developers
Classifier: License :: OSI Approved :: MIT License
Classifier: Natural Language :: English
Classifier: Operating System :: OS Independent
Classifier: Programming Language :: Python :: 3
Classifier: Programming Language :: Python :: 3.9
Classifier: Programming Language :: Python :: 3.10
Classifier: Programming Language :: Python :: 3.11
Classifier: Programming Language :: Python :: 3.12
Classifier: Topic :: Software Development :: Libraries
Project-URL: Bug Tracker, https://github.com/MartinHjelmare/leicaimage/issues
Project-URL: Changelog, https://github.com/MartinHjelmare/leicaimage/blob/main/CHANGELOG.md
Project-URL: Repository, https://github.com/MartinHjelmare/leicaimage
